hashfs/__init__.py
hashfs/__meta__.py
hashfs/_compat.py
hashfs/hashfs.py
hashfs/utils.py
hashfs-0.7.2.dist-info/AUTHORS.rst
hashfs-0.7.2.dist-info/LICENSE.rst
hashfs-0.7.2.dist-info/METADATA
hashfs-0.7.2.dist-info/WHEEL
hashfs-0.7.2.dist-info/top_level.txt
hashfs-0.7.2.dist-info/RECORD
